tee/__init__.py
tee/tee.py
tee-0.0.3.dist-info/METADATA
tee-0.0.3.dist-info/RECORD
tee-0.0.3.dist-info/WHEEL
tee-0.0.3.dist-info/top_level.txt
