Metadata-Version: 2.1
Name: tee
Version: 0.0.3
Summary: Python library to tee stderr/stdout temporarily
Home-page: https://github.com/algrebe/python-tee
Author: Anthony Rebello
Author-email: rebello.anthony@gmail.com
License: MIT License
Download-URL: https://github.com/algrebe/python-tee/tarball/0.0.3
Keywords: tee
Platform: UNKNOWN
Classifier: Programming Language :: Python :: 2.7
Classifier: Environment :: Console
Classifier: Intended Audience :: Developers
Classifier: License :: OSI Approved :: MIT License
